cmem_plugin_irdi/__init__.py
cmem_plugin_irdi/components.py
cmem_plugin_irdi/item_code.py
cmem_plugin_irdi/utils.py
cmem_plugin_irdi/vocabs/counterontology.ttl
cmem_plugin_irdi/workflow/__init__.py
cmem_plugin_irdi/workflow/irdi_plugin.py
cmem_plugin_irdi/workflow/logo.svg
cmem_plugin_irdi-0.8.0.dist-info/METADATA
cmem_plugin_irdi-0.8.0.dist-info/WHEEL
cmem_plugin_irdi-0.8.0.dist-info/licenses/LICENSE
cmem_plugin_irdi-0.8.0.dist-info/RECORD
